Metadata-Version: 2.1
Name: dcxht
Version: 1.2
Summary: Just random package
Home-page: https://github.com/naistrai/dcxcht
Download-URL: https://github.com/naistrai/dcxcht
Author: Naistrai
Author-email: rizkynaistrai@gmail.com
License: MIT
Project-URL: Documentation, https://packaging.python.org/tutorials/distributing-packages/
Project-URL: Funding, https://github.com/naistrai/dcxcht
Project-URL: Say Thanks!, https://github.com/naistrai/dcxcht
Project-URL: Source, https://github.com/naistrai/dcxcht
Project-URL: Tracker, https://github.com/naistrai/dcxcht/issues
Keywords: Just,Random,App
Classifier: Development Status :: 3 - Alpha
Classifier: Intended Audience :: Developers
Classifier: Topic :: Software Development :: Build Tools
Classifier: License :: OSI Approved :: MIT License
Classifier: Programming Language :: Python :: 3
Classifier: Programming Language :: Python :: 3.4
Classifier: Programming Language :: Python :: 3.5
Classifier: Programming Language :: Python :: 3.6
License-File: LICENSE
Requires-Dist: validators
Requires-Dist: beautifulsoup4
Requires-Dist: discordautochat
Requires-Dist: discorudo
